  <SpriteDatabase>
    <Sprite ID="1" Name="Baum1" FileName="tree1.png" Path="chars/" transparent_color="R0G128B128"/>
    <Sprite ID="2" Name="Hero1" FileName="Char1.png" Path="chars/" transparent_color="R0G128B128"/>
    <Sprite ID="3" Name="flare1" FileName="flare1.png" Path="animation/flare/" transparent_color="R0G0B0"/>
    <Sprite ID="4" Name="flare2" FileName="flare2.png" Path="animation/flare/" transparent_color="R0G0B0"/>
    <Sprite ID="5" Name="flare3" FileName="flare3.png" Path="animation/flare/" transparent_color="R0G0B0"/>
    <Sprite ID="6" Name="flare4" FileName="flare4.png" Path="animation/flare/" transparent_color="R0G0B0"/>
    <Sprite ID="7" Name="flare5" FileName="flare5.png" Path="animation/flare/" transparent_color="R0G0B0"/>
    <Sprite ID="8" Name="flare6" FileName="flare6.png" Path="animation/flare/" transparent_color="R0G0B0"/>
    <Sprite ID="9" Name="flare7" FileName="flare7.png" Path="animation/flare/" transparent_color="R0G0B0"/>
    <Sprite ID="10" Name="flare8" FileName="flare8.png" Path="animation/flare/" transparent_color="R0G0B0"/>
    <Sprite ID="11" Name="flare9" FileName="flare9.png" Path="animation/flare/" transparent_color="R0G0B0"/>
    <Sprite ID="12" Name="flare10" FileName="flare10.png" Path="animation/flare/" transparent_color="R0G0B0"/>
    <Sprite ID="13" Name="flare11" FileName="flare11.png" Path="animation/flare/" transparent_color="R0G0B0"/>
    <Sprite ID="14" Name="flare12" FileName="flare12.png" Path="animation/flare/" transparent_color="R0G0B0"/>
    <Sprite ID="15" Name="flare13" FileName="flare13.png" Path="animation/flare/" transparent_color="R0G0B0"/>
    <Sprite ID="16" Name="flare14" FileName="flare14.png" Path="animation/flare/" transparent_color="R0G0B0"/>
    <Sprite ID="17" Name="flare15" FileName="flare15.png" Path="animation/flare/" transparent_color="R0G0B0"/>
    <Sprite ID="18" Name="flare16" FileName="flare16.png" Path="animation/flare/" transparent_color="R0G0B0"/>
    <Sprite ID="19" Name="flare17" FileName="flare17.png" Path="animation/flare/" transparent_color="R0G0B0"/>
    <Sprite ID="20" Name="flare18" FileName="flare18.png" Path="animation/flare/" transparent_color="R0G0B0"/>
    <Sprite ID="21" Name="flare19" FileName="flare19.png" Path="animation/flare/" transparent_color="R0G0B0"/>
    <Sprite ID="22" Name="flare20" FileName="flare20.png" Path="animation/flare/" transparent_color="R0G0B0"/>
    <Sprite ID="23" Name="flare21" FileName="flare21.png" Path="animation/flare/" transparent_color="R0G0B0"/>
    <Sprite ID="24" Name="flare22" FileName="flare22.png" Path="animation/flare/" transparent_color="R0G0B0"/>
    <Sprite ID="25" Name="flare23" FileName="flare23.png" Path="animation/flare/" transparent_color="R0G0B0"/>
    <Sprite ID="26" Name="flare24" FileName="flare24.png" Path="animation/flare/" transparent_color="R0G0B0"/>
    <Sprite ID="27" Name="flare25" FileName="flare25.png" Path="animation/flare/" transparent_color="R0G0B0"/>
    <Sprite ID="28" Name="char1-walk-right-1" FileName="char1-walk-right-1.png" Path="chars/char1/walk-right/" transparent_color="R0G128B128"/>
    <Sprite ID="29" Name="char1-walk-right-2" FileName="char1-walk-right-2.png" Path="chars/char1/walk-right/" transparent_color="R0G128B128"/>
    <Sprite ID="30" Name="char1-walk-right-3" FileName="char1-walk-right-3.png" Path="chars/char1/walk-right/" transparent_color="R0G128B128"/>
  </SpriteDatabase>